Metadata-Version: 1.1
Name: omp-thread-count
Version: 0.2.1
Summary: A small utility to get the actual number of threads used by OpenMP via Cython bindings.
Home-page: https://github.com/rolando/omp-thread-count
Author: Rolando Espinoza
Author-email: rolando at rmax.io
License: MIT
Keywords: openmp,threads
Platform: UNKNOWN
Classifier: Development Status :: 3 - Alpha
Classifier: Intended Audience :: Developers
Classifier: License :: OSI Approved :: MIT License
Classifier: Natural Language :: English
Classifier: Programming Language :: Python :: 2
Classifier: Programming Language :: Python :: 2.7
Classifier: Programming Language :: Python :: 3
Classifier: Programming Language :: Python :: 3.5
